ctinspector/__init__.py
ctinspector/__main__.py
ctinspector/colorhelper.py
ctinspector/image.py
ctinspector/layer.py
ctinspector/report.py
ctinspector/tar.py
ctinspector/utils.py
ctinspector/version
ctinspector-0.0.3.dist-info/METADATA
ctinspector-0.0.3.dist-info/RECORD
ctinspector-0.0.3.dist-info/WHEEL
ctinspector-0.0.3.dist-info/entry_points.txt
ctinspector-0.0.3.dist-info/top_level.txt
